[
  { "domanda": "Qual è la scusa più pietosa che hai inventato per saltare la scuola?" },
  { "domanda": "Descrivi il tuo ultimo incubo usando solo termini culinari." },
  { "domanda": "Cosa stavi facendo l'ultima volta che hai fatto una figuraccia pazzesca?" },
  { "domanda": "Come spiegheresti cos'è un bidet a un alieno?" },
  { "domanda": "Qual è il tuo superpotere inutile ma di cui vai fierissimo?" },
  { "domanda": "Cosa penseresti se ti svegliassi e trovassi una mucca in salotto?" },
  { "domanda": "Racconta la tua peggior caduta in pubblico in due frasi." },
  { "domanda": "Qual è il motivo più stupido per cui hai litigato con qualcuno?" },
  { "domanda": "Descrivi il sapore del tuo dentifricio senza usare la parola 'menta'." },
  { "domanda": "Cosa faresti se vincessi un milione di euro ma potessi spenderli solo in roba inutile?" },
  { "domanda": "Qual è il pensiero più strano che fai mentre sei sotto la doccia?" },
  { "domanda": "Se il tuo animale domestico potesse parlare, quale segreto rivelerebbe su di te?" },
  { "domanda": "Descrivi la tua peggior esperienza dal parrucchiere." },
  { "domanda": "Cosa urleresti se un ladro entrasse in casa tua mentre sei sul wc?" },
  { "domanda": "Qual è l'oggetto più inutile che hai comprato su internet alle 3 di notte?" },
  { "domanda": "Descrivi un film famosissimo spiegandone la trama malissimo." },
  { "domanda": "Cosa c'è veramente alla fine dell'arcobaleno secondo te?" },
  { "domanda": "Qual è il commento più imbarazzante che un parente ti ha fatto a Natale?" },
  { "domanda": "Se la tua vita fosse una soap opera, quale sarebbe il colpo di scena di oggi?" },
  { "domanda": "Descrivi il tuo approccio al corteggiamento come se fossi un documentario di Piero Angela." },
  { "domanda": "Qual è il peggior regalo riciclato che hai mai fatto o ricevuto?" },
  { "domanda": "Cosa diresti al tuo io di dieci anni fa se avessi 5 secondi di tempo?" },
  { "domanda": "Spiega a un bambino perché il cielo è blu inventandoti una bugia cosmica." },
  { "domanda": "Qual è la fobia più assurda che hai (o che vorresti inventare)?" },
  { "domanda": "Se fossi un politico, qual è la prima legge stupida che approveresti?" },
  { "domanda": "Descrivi il tuo vestito ideale per affrontare l'apocalisse zombie." },
  { "domanda": "Qual è la cosa più schifosa che hai mangiato per sbaglio (o per scommessa)?" },
  { "domanda": "Come faresti a farti licenziare nel minor tempo possibile il primo giorno di lavoro?" },
  { "domanda": "Se potessi trasformarti in un oggetto di uso quotidiano, quale saresti e perché?" },
  { "domanda": "Qual è il peggior consiglio sentimentale che tu abbia mai ricevuto?" },
  { "domanda": "Descrivi la tua anima gemella usando solo difetti." },
  { "domanda": "Cosa fai di nascosto quando credi che nessuno ti stia guardando?" },
  { "domanda": "Sei bloccato in ascensore per 24 ore. Qual è il tuo piano di sopravvivenza?" },
  { "domanda": "Qual è l'ultima bugia bianca che hai detto per toglierti dall'imbarazzo?" },
  { "domanda": "Se potessi lanciare un incantesimo su un nemico, cosa gli faresti capitare di fastidioso?" },
  { "domanda": "Descrivi la cosa peggiore che hai trovato frugando dove non dovevi." },
  { "domanda": "Come conquisteresti il mondo usando solo uno stuzzicadenti e tanto carisma?" },
  { "domanda": "Qual è il tatuaggio più brutto che ti faresti se perdessi una scommessa?" },
  { "domanda": "Se la tua testa fosse un sito web, quale sarebbe la tua cronologia recente?" },
  { "domanda": "Spiega a tua nonna come funziona TikTok usando parole dell'Ottocento." },
  { "domanda": "Qual è la peggior frase che hai mai detto durante il primo appuntamento?" },
  { "domanda": "Se dovessi scappare dal paese in incognito, che nome e lavoro finto sceglieresti?" },
  { "domanda": "Qual è l'insulto più creativo che hai mai sentito o inventato?" },
  { "domanda": "Cosa c'è scritto nella chat di gruppo dei piccioni di città?" },
  { "domanda": "Descrivi il tuo stato d'animo attuale usando solo il nome di un animale e un verbo." },
  { "domanda": "Qual è il posto peggiore dove ti sei addormentato?" },
  { "domanda": "Se la sfiga avesse un volto, a chi o cosa assomiglierebbe?" },
  { "domanda": "Cosa faresti se scoprissi che i tuoi genitori sono spie sotto copertura?" },
  { "domanda": "Descrivi il panico di quando ti accorgi che nel bagno è finita la carta igienica." },
  { "domanda": "Qual è la cosa più da 'vecchio' che fai già regolarmente?" }
]